multihash/__init__.py
multihash/constants.py
multihash/multihash.py
py_multihash-2.0.1.dist-info/AUTHORS.rst
py_multihash-2.0.1.dist-info/LICENSE
py_multihash-2.0.1.dist-info/METADATA
py_multihash-2.0.1.dist-info/WHEEL
py_multihash-2.0.1.dist-info/top_level.txt
py_multihash-2.0.1.dist-info/RECORD
